jord/README.md
jord/__init__.py
jord/cad_utilities/README.md
jord/cad_utilities/__init__.py
jord/cad_utilities/oda_utilities.py
jord/fiona_utilities/README.md
jord/fiona_utilities/__init__.py
jord/fiona_utilities/deserialise.py
jord/gdal_utilities/README.md
jord/gdal_utilities/__init__.py
jord/gdal_utilities/cloning.py
jord/gdal_utilities/context.py
jord/gdal_utilities/conversion.py
jord/gdal_utilities/drivers.py
jord/gdal_utilities/enums.py
jord/gdal_utilities/error_handling.py
jord/gdal_utilities/importing.py
jord/gdal_utilities/persistence.py
jord/gdal_utilities/spatial_reference.py
jord/geojson_utilities/README.md
jord/geojson_utilities/__init__.py
jord/geojson_utilities/geometry_types.py
jord/geometric_analysis/README.md
jord/geometric_analysis/__init__.py
jord/geometric_analysis/center_line.py
jord/geometric_analysis/degrees_of_freedom.py
jord/geometric_analysis/intersections.py
jord/geometric_analysis/principal_axis.py
jord/geometric_analysis/simple_center_line.py
jord/geometric_analysis/tracing.py
jord/geopandas_utilities/README.md
jord/geopandas_utilities/__init__.py
jord/geopandas_utilities/geometry_filtering.py
jord/geopandas_utilities/importing.py
jord/geopandas_utilities/serialisation/README.md
jord/geopandas_utilities/serialisation/__init__.py
jord/geopandas_utilities/serialisation/well_known_binary.py
jord/geopandas_utilities/serialisation/well_known_text.py
jord/jax_utilities/__init__.py
jord/networkx_utilities/README.md
jord/networkx_utilities/__init__.py
jord/networkx_utilities/construction.py
jord/pandas_utilities/README.md
jord/pandas_utilities/__init__.py
jord/pandas_utilities/serde.py
jord/pdal_utilities/README.md
jord/pdal_utilities/__init__.py
jord/pillow_utilities/README.md
jord/pillow_utilities/__init__.py
jord/pillow_utilities/exif.py
jord/pillow_utilities/tiff.py
jord/qgis_utilities/README.md
jord/qgis_utilities/__init__.py
jord/qgis_utilities/attribute_table.py
jord/qgis_utilities/categorisation.py
jord/qgis_utilities/compatability.py
jord-0.10.3.dist-info/licenses/LICENSE.md
jord-0.10.3.dist-info/METADATA
jord-0.10.3.dist-info/WHEEL
jord-0.10.3.dist-info/top_level.txt
jord-0.10.3.dist-info/RECORD
