Metadata-Version: 2.4
Name: Jord
Version: 0.10.3
Summary: Geodata toolbox
Home-page: https://github.com/MapsPeople/jord
Download-URL: https://github.com/MapsPeople/jord/releases
Author: Christian Heider Lindbjerg
Author-email: chen@mapspeople.dk
Maintainer: Christian Heider Lindbjerg
Maintainer-email: chen@mapspeople.dk
License: Apache License, Version 2.0
Keywords: python computer vision neo droid
Classifier: Development Status :: 4 - Beta
Classifier: Environment :: Console
Classifier: Intended Audience :: End Users/Desktop
Classifier: Intended Audience :: Developers
Classifier: License :: OSI Approved :: Apache Software License
Classifier: Operating System :: MacOS :: MacOS X
Classifier: Operating System :: Microsoft :: Windows
Classifier: Operating System :: POSIX
Classifier: Operating System :: OS Independent
Classifier: Programming Language :: Python :: 3
Classifier: Natural Language :: English
Requires-Python: >=3.6
License-File: LICENSE.md
Requires-Dist: apppath>=1.0.7
Requires-Dist: draugr>=1.2.1
Requires-Dist: numpy>=1.20.0
Requires-Dist: pyzmq>=1.1.1
Requires-Dist: sorcery>=0.2.0
Requires-Dist: sympy>=1.1.1
Requires-Dist: tqdm>=1.1.1
Requires-Dist: warg>=1.4.9
Provides-Extra: shapely
Requires-Dist: shapely; extra == "shapely"
Requires-Dist: pyproj; extra == "shapely"
Provides-Extra: networkx
Requires-Dist: osmnx>=2.0.5; extra == "networkx"
Requires-Dist: networkx; extra == "networkx"
Provides-Extra: samples
Provides-Extra: dev
Requires-Dist: furo; extra == "dev"
Requires-Dist: tqdm>=1.1.1; extra == "dev"
Requires-Dist: fiona>=1.1.1; extra == "dev"
Requires-Dist: pre-commit>=2.17.0; extra == "dev"
Requires-Dist: warg>=1.4.9; extra == "dev"
Requires-Dist: pip>=22.1.2; extra == "dev"
Requires-Dist: geopandas; extra == "dev"
Requires-Dist: shapely; extra == "dev"
Requires-Dist: draugr>=1.2.1; extra == "dev"
Requires-Dist: Pillow; extra == "dev"
Requires-Dist: sorcery>=0.2.0; extra == "dev"
Requires-Dist: sympy>=1.1.1; extra == "dev"
Requires-Dist: coveralls>=1.6.0; extra == "dev"
Requires-Dist: PyQt6>=6.0.0; extra == "dev"
Requires-Dist: pytest-cov>=2.11.1; extra == "dev"
Requires-Dist: apppath>=1.0.7; extra == "dev"
Requires-Dist: osmnx>=2.0.5; extra == "dev"
Requires-Dist: pytest>=4.4.1; extra == "dev"
Requires-Dist: pyzmq>=1.1.1; extra == "dev"
Requires-Dist: pytest>=4.3.0; extra == "dev"
Requires-Dist: mock; extra == "dev"
Requires-Dist: twine>=1.13.0; extra == "dev"
Requires-Dist: networkx; extra == "dev"
Requires-Dist: numpy>=1.20.0; extra == "dev"
Requires-Dist: sphinxcontrib-programoutput; extra == "dev"
Requires-Dist: pyproj; extra == "dev"
Requires-Dist: wheel>=0.33.0; extra == "dev"
Requires-Dist: black[jupyter]>=21.5b0; extra == "dev"
Requires-Dist: sphinx>=4.0.1; extra == "dev"
Requires-Dist: importlib-metadata; extra == "dev"
Requires-Dist: importlib-resources; extra == "dev"
Requires-Dist: ezdxf; extra == "dev"
Provides-Extra: geometric-analysis
Requires-Dist: momepy; extra == "geometric-analysis"
Provides-Extra: geopandas
Requires-Dist: geopandas; extra == "geopandas"
Provides-Extra: pil
Requires-Dist: Pillow; extra == "pil"
Provides-Extra: tests
Requires-Dist: PyQt6>=6.0.0; extra == "tests"
Requires-Dist: pyproj; extra == "tests"
Requires-Dist: networkx; extra == "tests"
Requires-Dist: fiona>=1.1.1; extra == "tests"
Requires-Dist: osmnx>=2.0.5; extra == "tests"
Requires-Dist: geopandas; extra == "tests"
Requires-Dist: importlib-metadata; extra == "tests"
Requires-Dist: pytest>=4.4.1; extra == "tests"
Requires-Dist: importlib-resources; extra == "tests"
Requires-Dist: shapely; extra == "tests"
Requires-Dist: ezdxf; extra == "tests"
Requires-Dist: Pillow; extra == "tests"
Requires-Dist: mock; extra == "tests"
Provides-Extra: extra
Provides-Extra: cad
Requires-Dist: ezdxf; extra == "cad"
Provides-Extra: docs
Requires-Dist: furo; extra == "docs"
Requires-Dist: sphinxcontrib-programoutput; extra == "docs"
Requires-Dist: sphinx>=4.0.1; extra == "docs"
Provides-Extra: setup
Provides-Extra: qgis
Requires-Dist: PyQt6>=6.0.0; extra == "qgis"
Provides-Extra: legacy
Requires-Dist: importlib-resources; extra == "legacy"
Requires-Dist: importlib-metadata; extra == "legacy"
Provides-Extra: gdal
Provides-Extra: qt
Requires-Dist: PyQt6>=6.0.0; extra == "qt"
Provides-Extra: pdal
Requires-Dist: PDAL>=3.3.0; extra == "pdal"
Requires-Dist: numpy>=1.20.0; extra == "pdal"
Provides-Extra: fiona
Requires-Dist: fiona>=1.1.1; extra == "fiona"
Provides-Extra: all
Requires-Dist: furo; extra == "all"
Requires-Dist: tqdm>=1.1.1; extra == "all"
Requires-Dist: fiona>=1.1.1; extra == "all"
Requires-Dist: pre-commit>=2.17.0; extra == "all"
Requires-Dist: warg>=1.4.9; extra == "all"
Requires-Dist: pip>=22.1.2; extra == "all"
Requires-Dist: geopandas; extra == "all"
Requires-Dist: shapely; extra == "all"
Requires-Dist: draugr>=1.2.1; extra == "all"
Requires-Dist: sorcery>=0.2.0; extra == "all"
Requires-Dist: Pillow; extra == "all"
Requires-Dist: sympy>=1.1.1; extra == "all"
Requires-Dist: coveralls>=1.6.0; extra == "all"
Requires-Dist: PyQt6>=6.0.0; extra == "all"
Requires-Dist: pytest-cov>=2.11.1; extra == "all"
Requires-Dist: apppath>=1.0.7; extra == "all"
Requires-Dist: osmnx>=2.0.5; extra == "all"
Requires-Dist: momepy; extra == "all"
Requires-Dist: pytest>=4.4.1; extra == "all"
Requires-Dist: pyzmq>=1.1.1; extra == "all"
Requires-Dist: pytest>=4.3.0; extra == "all"
Requires-Dist: mock; extra == "all"
Requires-Dist: twine>=1.13.0; extra == "all"
Requires-Dist: networkx; extra == "all"
Requires-Dist: numpy>=1.20.0; extra == "all"
Requires-Dist: sphinxcontrib-programoutput; extra == "all"
Requires-Dist: PDAL>=3.3.0; extra == "all"
Requires-Dist: pyproj; extra == "all"
Requires-Dist: wheel>=0.33.0; extra == "all"
Requires-Dist: black[jupyter]>=21.5b0; extra == "all"
Requires-Dist: sphinx>=4.0.1; extra == "all"
Requires-Dist: importlib-metadata; extra == "all"
Requires-Dist: importlib-resources; extra == "all"
Requires-Dist: ezdxf; extra == "all"
Dynamic: author
Dynamic: author-email
Dynamic: classifier
Dynamic: description
Dynamic: description-content-type
Dynamic: download-url
Dynamic: home-page
Dynamic: keywords
Dynamic: license
Dynamic: license-file
Dynamic: maintainer
Dynamic: maintainer-email
Dynamic: provides-extra
Dynamic: requires-dist
Dynamic: requires-python
Dynamic: summary
